{
  "kind": "singleType",
  "collectionName": "informacaos",
  "info": {
    "singularName": "informacao",
    "pluralName": "informacaos",
    "displayName": "Informação",
    "description": ""
  },
  "options": {
    "draftAndPublish": true
  },
  "pluginOptions": {},
  "attributes": {
    "siteTitle": {
      "type": "string",
      "required": true
    },
    "addressText": {
      "type": "string"
    },
    "addressLink": {
      "type": "string"
    },
    "facebookLink": {
      "type": "string"
    },
    "instagramLink": {
      "type": "string"
    },
    "linkedinLink": {
      "type": "string"
    },
    "youtubeLink": {
      "type": "string"
    },
    "whatsappText": {
      "type": "string"
    },
    "whatsappLink": {
      "type": "string"
    },
    "telephone": {
      "type": "string"
    },
    "email": {
      "type": "email"
    }
  }
}
